firebase_auth/__init__.py
firebase_auth/apps.py
firebase_auth/authentication.py
firebase_auth/forms.py
firebase_auth/models.py
django_graphene_firebase_auth-0.0.33.dist-info/LICENSE
django_graphene_firebase_auth-0.0.33.dist-info/METADATA
django_graphene_firebase_auth-0.0.33.dist-info/WHEEL
django_graphene_firebase_auth-0.0.33.dist-info/top_level.txt
django_graphene_firebase_auth-0.0.33.dist-info/RECORD
